nonebot_plugin_discord_message_bridge/__init__.py
nonebot_plugin_discord_message_bridge/config.py
nonebot_plugin_discord_message_bridge/global_vars.py
nonebot_plugin_discord_message_bridge/bots/discordbot.py
nonebot_plugin_discord_message_bridge/utils/download.py
nonebot_plugin_discord_message_bridge/utils/forward.py
nonebot_plugin_discord_message_bridge/utils/local.py
nonebot_plugin_discord_message_bridge/utils/send.py
nonebot_plugin_discord_message_bridge/utils/yamlloader.py
nonebot_plugin_discord_message_bridge-1.4.0.dist-info/licenses/LICENSE
nonebot_plugin_discord_message_bridge-1.4.0.dist-info/METADATA
nonebot_plugin_discord_message_bridge-1.4.0.dist-info/WHEEL
nonebot_plugin_discord_message_bridge-1.4.0.dist-info/top_level.txt
nonebot_plugin_discord_message_bridge-1.4.0.dist-info/RECORD
