Metadata-Version: 2.4
Name: nonebot-plugin-discord-message-bridge
Version: 1.4.0
Summary: Discord - QQ 消息转发插件
Author-email: xxtg666 <xxtg666@gmail.com>
License: GPL-3
Requires-Python: >=3.9
License-File: LICENSE
Requires-Dist: nonebot2
Requires-Dist: nonebot-adapter-onebot
Requires-Dist: discord-py
Requires-Dist: nonebot2[fastapi]
Requires-Dist: httpx
Dynamic: license-file
